[
    {
        "id": 1,
        "category": "Sea Creatures",
        "name": "Seaweed",
        "icon": "assets/sea-creatures/Seaweed.png",
        "sellPrice": 600,
        "shadowSize": "Large",
        "shadowMovement": "Stationary",
        "time": "All day",
        "north": [1,1,1,1,1,1,1,0,0,1,1,1],
        "south": [1,0,0,1,1,1,1,1,1,1,1,1]
      },
      {
        "id": 2,
        "category": "Sea Creatures",
        "name": "Sea grapes",
        "icon": "assets/sea-creatures/SeaGrapes.png",
        "sellPrice": 900,
        "shadowSize": "Small",
        "shadowMovement": "Stationary",
        "time": "All day",
        "north": [0,0,0,0,0,1,1,1,1,0,0,0],
        "south": [1,1,1,0,0,0,0,0,0,0,0,1]
      },
      {
        "id": 3,
        "category": "Sea Creatures",
        "name": "Sea cucumber",
        "icon": "assets/sea-creatures/SeaCucumber.png",
        "sellPrice": 500,
        "shadowSize": "Medium",
        "shadowMovement": "Very slow",
        "time": "All day",
        "north": [1,1,1,1,0,0,0,0,0,0,1,1],
        "south": [0,0,0,0,1,1,1,1,1,1,0,0]
      },
      {
        "id": 4,
        "category": "Sea Creatures",
        "name": "Sea pig",
        "icon": "assets/sea-creatures/SeaPig.png",
        "sellPrice": 10000,
        "shadowSize": "Small",
        "shadowMovement": "Very fast",
        "time": "4 PM - 9 AM",
        "north": [1,1,0,0,0,0,0,0,0,0,1,1],
        "south": [0,0,0,0,1,1,1,1,0,0,0,0]
      },
      {
        "id": 5,
        "category": "Sea Creatures",
        "name": "Sea star",
        "icon": "assets/sea-creatures/SeaStar.png",
        "sellPrice": 500,
        "shadowSize": "Small",
        "shadowMovement": "Very slow",
        "time": "All day",
        "north": [1,1,1,1,1,1,1,1,1,1,1,1],
        "south": [1,1,1,1,1,1,1,1,1,1,1,1]
      },
      {
        "id": 6,
        "category": "Sea Creatures",
        "name": "Sea urchin",
        "icon": "assets/sea-creatures/SeaUrchin.png",
        "sellPrice": 1700,
        "shadowSize": "Small",
        "shadowMovement": "Slow",
        "time": "All day",
        "north": [0,0,0,0,1,1,1,1,1,0,0,0],
        "south": [1,1,1,0,0,0,0,0,0,0,1,1]
      },
      {
        "id": 7,
        "category": "Sea Creatures",
        "name": "Slate pencil urchin",
        "icon": "assets/sea-creatures/SlatePencilUrchin.png",
        "sellPrice": 2000,
        "shadowSize": "Medium",
        "shadowMovement": "Medium",
        "time": "4 PM - 9 AM",
        "north": [0,0,0,0,1,1,1,1,1,0,0,0],
        "south": [1,1,1,0,0,0,0,0,0,0,1,1]
      },
      {
        "id": 8,
        "category": "Sea Creatures",
        "name": "Sea anemone",
        "icon": "assets/sea-creatures/SeaAnemone.png",
        "sellPrice": 500,
        "shadowSize": "Large",
        "shadowMovement": "Stationary",
        "time": "All day",
        "north": [1,1,1,1,1,1,1,1,1,1,1,1],
        "south": [1,1,1,1,1,1,1,1,1,1,1,1]
      },
      {
        "id": 9,
        "category": "Sea Creatures",
        "name": "Moon jellyfish",
        "icon": "assets/sea-creatures/MoonJellyfish.png",
        "sellPrice": 600,
        "shadowSize": "Small",
        "shadowMovement": "Very slow",
        "time": "All day",
        "north": [0,0,0,0,0,0,1,1,1,0,0,0],
        "south": [1,1,1,0,0,0,0,0,0,0,0,0]
      },
      {
        "id": 10,
        "category": "Sea Creatures",
        "name": "Sea slug",
        "icon": "assets/sea-creatures/SeaSlug.png",
        "sellPrice": 600,
        "shadowSize": "Tiny",
        "shadowMovement": "Very slow",
        "time": "All day",
        "north": [1,1,1,1,1,1,1,1,1,1,1,1],
        "south": [1,1,1,1,1,1,1,1,1,1,1,1]
      },
      {
        "id": 11,
        "category": "Sea Creatures",
        "name": "Pearl oyster",
        "icon": "assets/sea-creatures/PearlOyster.png",
        "sellPrice": 2800,
        "shadowSize": "Small",
        "shadowMovement": "Medium",
        "time": "All day",
        "north": [1,1,1,1,1,1,1,1,1,1,1,1],
        "south": [1,1,1,1,1,1,1,1,1,1,1,1]
      },
      {
        "id": 12,
        "category": "Sea Creatures",
        "name": "Mussel",
        "icon": "assets/sea-creatures/Mussel.png",
        "sellPrice": 1500,
        "shadowSize": "Small",
        "shadowMovement": "Slow",
        "time": "All day",
        "north": [0,0,0,0,0,1,1,1,1,1,1,1],
        "south": [1,1,1,1,1,1,0,0,0,0,0,1]
      },
      {
        "id": 13,
        "category": "Sea Creatures",
        "name": "Oyster",
        "icon": "assets/sea-creatures/Oyster.png",
        "sellPrice": 1100,
        "shadowSize": "Small",
        "shadowMovement": "Slow",
        "time": "All day",
        "north": [1,1,0,0,0,0,0,0,1,1,1,1],
        "south": [0,0,1,1,1,1,1,1,0,0,0,0]
      },
      {
        "id": 14,
        "category": "Sea Creatures",
        "name": "Scallop",
        "icon": "assets/sea-creatures/Scallop.png",
        "sellPrice": 1200,
        "shadowSize": "Medium",
        "shadowMovement": "Slow",
        "time": "All day",
        "north": [1,1,1,1,1,1,1,1,1,1,1,1],
        "south": [1,1,1,1,1,1,1,1,1,1,1,1]
      },
      {
        "id": 15,
        "category": "Sea Creatures",
        "name": "Whelk",
        "icon": "assets/sea-creatures/Whelk.png",
        "sellPrice": 1000,
        "shadowSize": "Small",
        "shadowMovement": "Slow",
        "time": "All day",
        "north": [1,1,1,1,1,1,1,1,1,1,1,1],
        "south": [1,1,1,1,1,1,1,1,1,1,1,1]
      },
      {
        "id": 16,
        "category": "Sea Creatures",
        "name": "Turban shell",
        "icon": "assets/sea-creatures/TurbanShell.png",
        "sellPrice": 1000,
        "shadowSize": "Small",
        "shadowMovement": "Slow",
        "time": "All day",
        "north": [0,0,1,1,1,0,0,0,1,1,1,1],
        "south": [0,0,1,1,1,0,0,0,1,1,1,1]
      },
      {
        "id": 17,
        "category": "Sea Creatures",
        "name": "Abalone",
        "icon": "assets/sea-creatures/Abalone.png",
        "sellPrice": 2000,
        "shadowSize": "Medium",
        "shadowMovement": "Medium",
        "time": "4 PM - 9 AM",
        "north": [1,0,0,0,0,1,1,1,1,1,1,1],
        "south": [1,1,1,1,1,1,1,0,0,0,0,1]
      },
      {
        "id": 18,
        "category": "Sea Creatures",
        "name": "Gigas giant clam",
        "icon": "assets/sea-creatures/GigasGiantClam.png",
        "sellPrice": 15000,
        "shadowSize": "Very large",
        "shadowMovement": "Very fast",
        "time": "All day",
        "north": [0,0,0,0,1,1,1,1,1,0,0,0],
        "south": [1,1,1,0,0,0,0,0,0,0,1,1]
      },
      {
        "id": 19,
        "category": "Sea Creatures",
        "name": "Chambered nautilus",
        "icon": "assets/sea-creatures/ChamberedNautilus.png",
        "sellPrice": 1800,
        "shadowSize": "Medium",
        "shadowMovement": "Medium",
        "time": "4 PM - 9 AM",
        "north": [0,0,1,1,1,1,0,0,1,1,1,0],
        "south": [0,0,1,1,1,1,0,0,1,1,1,0]
      },
      {
        "id": 20,
        "category": "Sea Creatures",
        "name": "Octopus",
        "icon": "assets/sea-creatures/Octopus.png",
        "sellPrice": 1200,
        "shadowSize": "Medium",
        "shadowMovement": "Slow",
        "time": "All day",
        "north": [1,1,1,1,1,1,1,1,1,1,1,1],
        "south": [1,1,1,1,1,1,1,1,1,1,1,1]
      },
      {
        "id": 21,
        "category": "Sea Creatures",
        "name": "Umbrella octopus",
        "icon": "assets/sea-creatures/UmbrellaOctopus.png",
        "sellPrice": 6000,
        "shadowSize": "Small",
        "shadowMovement": "Fast",
        "time": "All day",
        "north": [0,0,1,1,1,0,0,0,1,1,1,0],
        "south": [0,0,1,1,1,0,0,0,1,1,1,0]
      },
      {
        "id": 22,
        "category": "Sea Creatures",
        "name": "Vampire squid",
        "icon": "assets/sea-creatures/VampireSquid.png",
        "sellPrice": 10000,
        "shadowSize": "Medium",
        "shadowMovement": "Very fast",
        "time": "4 PM - 9 AM",
        "north": [0,0,0,0,1,1,1,1,0,0,0,0],
        "south": [1,1,0,0,0,0,0,0,0,0,1,1]
      },
      {
        "id": 23,
        "category": "Sea Creatures",
        "name": "Firefly squid",
        "icon": "assets/sea-creatures/FireflySquid.png",
        "sellPrice": 1400,
        "shadowSize": "Tiny",
        "shadowMovement": "Slow",
        "time": "9 PM - 4 AM",
        "north": [0,0,1,1,1,1,0,0,0,0,0,0],
        "south": [0,0,0,0,0,0,0,0,1,1,1,1]
      },
      {
        "id": 24,
        "category": "Sea Creatures",
        "name": "Gazami crab",
        "icon": "assets/sea-creatures/GazamiCrab.png",
        "sellPrice": 2200,
        "shadowSize": "Medium",
        "shadowMovement": "Medium",
        "time": "All day",
        "north": [0,0,0,0,0,1,1,1,1,1,1,0],
        "south": [1,1,1,1,1,0,0,0,0,0,0,1]
      },
      {
        "id": 25,
        "category": "Sea Creatures",
        "name": "Dungeness crab",
        "icon": "assets/sea-creatures/DungenessCrab.png",
        "sellPrice": 1900,
        "shadowSize": "Medium",
        "shadowMovement": "Medium",
        "time": "All day",
        "north": [1,1,1,1,1,0,0,0,0,0,1,1],
        "south": [0,0,0,0,1,1,1,1,1,1,1,0]
      },
      {
        "id": 26,
        "category": "Sea Creatures",
        "name": "Snow crab",
        "icon": "assets/sea-creatures/SnowCrab.png",
        "sellPrice": 6000,
        "shadowSize": "Large",
        "shadowMovement": "Fast",
        "time": "All day",
        "north": [1,1,1,1,1,0,0,0,0,0,1,1],
        "south": [0,0,0,0,1,1,1,1,1,1,1,0]
      },
      {
        "id": 27,
        "category": "Sea Creatures",
        "name": "Red king crab",
        "icon": "assets/sea-creatures/RedKingCrab.png",
        "sellPrice": 8000,
        "shadowSize": "Large",
        "shadowMovement": "Very fast",
        "time": "All day",
        "north": [1,1,1,1,1,0,0,0,0,0,1,1],
        "south": [0,0,0,0,1,1,1,1,1,1,1,0]
      },
      {
        "id": 28,
        "category": "Sea Creatures",
        "name": "Acorn barnacle",
        "icon": "assets/sea-creatures/AcornBarnacle.png",
        "sellPrice": 600,
        "shadowSize": "Tiny",
        "shadowMovement": "Stationary",
        "time": "All day",
        "north": [1,1,1,1,1,1,1,1,1,1,1,1],
        "south": [1,1,1,1,1,1,1,1,1,1,1,1]
      },
      {
        "id": 29,
        "category": "Sea Creatures",
        "name": "Spider crab",
        "icon": "assets/sea-creatures/SpiderCrab.png",
        "sellPrice": 12000,
        "shadowSize": "Very large",
        "shadowMovement": "Very fast",
        "time": "All day",
        "north": [0,0,1,1,0,0,0,0,0,0,0,0],
        "south": [0,0,0,0,0,0,0,0,1,1,0,0]
      },
      {
        "id": 30,
        "category": "Sea Creatures",
        "name": "Tiger prawn",
        "icon": "assets/sea-creatures/TigerPrawn.png",
        "sellPrice": 3000,
        "shadowSize": "Small",
        "shadowMovement": "Medium",
        "time": "4 PM - 9 AM",
        "north": [0,0,0,0,0,0,0,0,0,0,0,0],
        "south": [0,0,0,0,0,0,0,0,0,0,0,0]
      },
      {
        "id": 31,
        "category": "Sea Creatures",
        "name": "Sweet shrimp",
        "icon": "assets/sea-creatures/SweetShrimp.png",
        "sellPrice": "ÿ1400ÿ",
        "shadowSize": "Small",
        "shadowMovement": "Slow",
        "time": "4 PM - 9 AM",
        "north": [0,0,0,0,0,0,0,0,0,0,0,0],
        "south": [0,0,0,0,0,0,0,0,0,0,0,0]
      },
      {
        "id": 32,
        "category": "Sea Creatures",
        "name": "Mantis shrimp",
        "icon": "assets/sea-creatures/MantisShrimp.png",
        "sellPrice": 2500,
        "shadowSize": "Small",
        "shadowMovement": "Medium",
        "time": "4 PM - 9 AM",
        "north": [1,1,1,1,1,1,1,1,1,1,1,1],
        "south": [1,1,1,1,1,1,1,1,1,1,1,1]
      },
      {
        "id": 33,
        "category": "Sea Creatures",
        "name": "Spiny lobster",
        "icon": "assets/sea-creatures/SpinyLobster.png",
        "sellPrice": 5000,
        "shadowSize": "Large",
        "shadowMovement": "Fast",
        "time": "9 PM - 4 AM",
        "north": [0,0,0,0,0,0,0,0,0,1,1,1],
        "south": [0,0,0,1,1,1,0,0,0,0,0,0]
      },
      {
        "id": 34,
        "category": "Sea Creatures",
        "name": "Lobster",
        "icon": "assets/sea-creatures/Lobster.png",
        "sellPrice": 4500,
        "shadowSize": "Large",
        "shadowMovement": "Fast",
        "time": "All day",
        "north": [1,0,0,1,1,1,0,0,0,0,0,1],
        "south": [0,0,0,0,0,1,1,0,0,1,1,1]
      },
      {
        "id": 35,
        "category": "Sea Creatures",
        "name": "Giant isopod",
        "icon": "assets/sea-creatures/GiantIsopod.png",
        "sellPrice": 12000,
        "shadowSize": "Medium",
        "shadowMovement": "Very fast",
        "time": "9 AM - 4 PM; 9 PM - 4 AM",
        "north": [0,0,0,0,0,0,1,1,1,1,0,0],
        "south": [1,1,1,1,0,0,0,0,0,0,0,0]
      },
      {
        "id": 36,
        "category": "Sea Creatures",
        "name": "Horseshoe crab",
        "icon": "assets/sea-creatures/HorseshoeCrab.png",
        "sellPrice": 2500,
        "shadowSize": "Medium",
        "shadowMovement": "Medium",
        "time": "9 PM - 4 AM",
        "north": [0,0,0,0,0,0,1,1,1,0,0,0],
        "south": [1,1,1,0,0,0,0,0,0,0,0,0]
      },
      {
        "id": 37,
        "category": "Sea Creatures",
        "name": "Sea pineapple",
        "icon": "assets/sea-creatures/SeaPineapple.png",
        "sellPrice": 500,
        "shadowSize": "Small",
        "shadowMovement": "Slow",
        "time": "All day",
        "north": [0,0,0,1,1,1,1,1,0,0,0,0],
        "south": [1,1,0,0,0,0,0,0,0,1,1,1]
      },
      {
        "id": 38,
        "category": "Sea Creatures",
        "name": "Spotted garden eel",
        "icon": "assets/sea-creatures/SpottedGardenEel.png",
        "sellPrice": 1100,
        "shadowSize": "Small",
        "shadowMovement": "Slow",
        "time": "4 AM - 9 PM",
        "north": [0,0,0,0,1,1,1,1,1,1,0,0],
        "south": [1,1,1,1,0,0,0,0,0,0,1,1]
      },
      {
        "id": 39,
        "category": "Sea Creatures",
        "name": "Flatworm",
        "icon": "assets/sea-creatures/Flatworm.png",
        "sellPrice": 700,
        "shadowSize": "Tiny",
        "shadowMovement": "Very slow",
        "time": "4 PM - 9 AM",
        "north": [0,0,0,0,0,0,0,1,1,0,0,0],
        "south": [0,1,1,0,0,0,0,0,0,0,0,0]
      },
      {
        "id": 40,
        "category": "Sea Creatures",
        "name": "Venus' flower basket",
        "icon": "assets/sea-creatures/VenusFlowerBasket.png",
        "sellPrice": 5000,
        "shadowSize": "Medium",
        "shadowMovement": "Fast",
        "time": "All day",
        "north": [1,1,0,0,0,0,0,0,0,1,1,1],
        "south": [0,0,0,1,1,1,1,1,0,0,0,0]
      }
]